{
  "type": "Feature",
  "stac_version": "1.0.0",
  "id": "BP28_2000_0816",
  "links": [
    { "rel": "self", "href": "./BP28_2000_0816.json", "type": "application/json" },
    { "rel": "collection", "href": "./collection.json", "type": "application/json" },
    { "rel": "parent", "href": "./collection.json", "type": "application/json" }
  ],
  "assets": {
    "visual": {
      "href": "./BP28_2000_0816.tiff",
      "type": "image/tiff; application=geotiff; profile=cloud-optimized",
      "file:checksum": "12209ee288e7a37ab45c3e3deb7eaf320a2bb5011ca89b8da67526e252a83eb56583"
    }
  },
  "stac_extensions": ["https://stac-extensions.github.io/file/v2.0.0/schema.json"],
  "properties": { "start_datetime": "2011-02-11T11:00:00Z", "end_datetime": "2012-02-03T11:00:00Z", "datetime": null },
  "geometry": {
    "type": "Polygon",
    "coordinates": [
      [
        [173.8837918, -40.9364641],
        [173.8839648, -40.9494345],
        [173.8953695, -40.9493465],
        [173.8951943, -40.9363761],
        [173.8837918, -40.9364641]
      ]
    ]
  },
  "bbox": [173.8837918, -40.9494345, 173.8953695, -40.9363761],
  "collection": "01GT088TWXJ52AZEE352PPQZ23"
}
