{
  "type": "Feature",
  "stac_version": "1.0.0",
  "id": "BX23_500_001072",
  "links": [
    { "rel": "self", "href": "./BX23_500_001072.json", "type": "application/json" },
    { "rel": "collection", "href": "./collection.json", "type": "application/json" },
    { "rel": "parent", "href": "./collection.json", "type": "application/json" }
  ],
  "assets": {
    "visual": {
      "href": "./BX23_500_001072.tiff",
      "type": "image/tiff; application=geotiff; profile=cloud-optimized",
      "file:checksum": "1220e6c33da6bec92b5c528c293afe373541b075dd310b742d6faf96178464035358"
    }
  },
  "stac_extensions": ["https://stac-extensions.github.io/file/v2.0.0/schema.json"],
  "properties": { "start_datetime": "2016-01-21T11:00:00Z", "end_datetime": "2016-02-19T11:00:00Z", "datetime": null },
  "geometry": {
    "type": "Polygon",
    "coordinates": [
      [
        [172.4691196, -43.4416677],
        [172.4690913, -43.4449092],
        [172.4720571, -43.4449229],
        [172.4720853, -43.4416814],
        [172.4691196, -43.4416677]
      ]
    ]
  },
  "bbox": [172.4690913, -43.4449229, 172.4720853, -43.4416677],
  "collection": "01GSR3FCJE4TBXZ2YD5D0ZCYGJ"
}
