{
  "type": "Feature",
  "stac_version": "1.0.0",
  "id": "CE17_1000_3710",
  "links": [
    { "rel": "self", "href": "./CE17_1000_3710.json", "type": "application/json" },
    { "rel": "collection", "href": "./collection.json", "type": "application/json" },
    { "rel": "parent", "href": "./collection.json", "type": "application/json" }
  ],
  "assets": {
    "visual": {
      "href": "./CE17_1000_3710.tiff",
      "type": "image/tiff; application=geotiff; profile=cloud-optimized",
      "file:checksum": "12202ed203e08f652bac67e7659063e6b3a12394461df08fc841c599cc0b530d8801"
    }
  },
  "stac_extensions": ["https://stac-extensions.github.io/file/v2.0.0/schema.json"],
  "properties": { "start_datetime": "2018-01-13T11:00:00Z", "end_datetime": "2019-04-06T11:00:00Z", "datetime": null },
  "geometry": {
    "type": "Polygon",
    "coordinates": [
      [
        [170.4251064, -45.9158322],
        [170.4248068, -45.922306],
        [170.4309908, -45.9224453],
        [170.4312898, -45.9159714],
        [170.4251064, -45.9158322]
      ]
    ]
  },
  "bbox": [170.4248068, -45.9224453, 170.4312898, -45.9158322],
  "collection": "01GYC6EZD79G3MAMSP37X4HAQX"
}
