{
  "type": "Feature",
  "stac_version": "1.0.0",
  "id": "BQ31_500_039088",
  "links": [
    { "rel": "self", "href": "./BQ31_500_039088.json", "type": "application/json" },
    { "rel": "collection", "href": "./collection.json", "type": "application/json" },
    { "rel": "parent", "href": "./collection.json", "type": "application/json" }
  ],
  "assets": {
    "visual": {
      "href": "./BQ31_500_039088.tiff",
      "type": "image/tiff; application=geotiff; profile=cloud-optimized",
      "file:checksum": "122028cf41663baefc5f72e12b033dcd3c225b1d4dbed8b7bba0847c8658388f46f8"
    }
  },
  "stac_extensions": ["https://stac-extensions.github.io/file/v2.0.0/schema.json"],
  "properties": { "start_datetime": "2017-02-23T11:00:00Z", "end_datetime": "2017-03-04T11:00:00Z", "datetime": null },
  "geometry": {
    "type": "Polygon",
    "coordinates": [
      [
        [174.8255679, -41.2820929],
        [174.8256583, -41.285334],
        [174.8285229, -41.2852886],
        [174.8284324, -41.2820474],
        [174.8255679, -41.2820929]
      ]
    ]
  },
  "bbox": [174.8255679, -41.285334, 174.8285229, -41.2820474],
  "collection": "01GYB46Y83WQYV36TYRPE4PH23"
}
