{
  "type": "Feature",
  "stac_version": "1.0.0",
  "id": "BH31_2K_1506",
  "links": [
    { "rel": "self", "href": "./BH31_2K_1506.json", "type": "application/json" },
    { "rel": "collection", "href": "./collection.json", "type": "application/json" },
    { "rel": "parent", "href": "./collection.json", "type": "application/json" }
  ],
  "assets": {
    "visual": {
      "href": "./BH31_2K_1506.tiff",
      "type": "image/tiff; application=geotiff; profile=cloud-optimized",
      "file:checksum": "122028c7cca476014dc81b0fffec9288b26af6b831c8f940fc06bad8834ed80fbf40"
    }
  },
  "stac_extensions": ["https://stac-extensions.github.io/file/v2.0.0/schema.json"],
  "properties": { "start_datetime": "2016-10-30T11:00:00Z", "end_datetime": "2018-03-10T11:00:00Z", "datetime": null },
  "geometry": {
    "type": "Polygon",
    "coordinates": [
      [
        [174.5814291, -39.0738319],
        [174.5817188, -39.0868031],
        [174.5928181, -39.086652],
        [174.5925264, -39.0736808],
        [174.5814291, -39.0738319]
      ]
    ]
  },
  "bbox": [174.5814291, -39.0868031, 174.5928181, -39.0736808],
  "collection": "01GYBVY2FRRHTGSHK26JHD922E"
}
