{
  "type": "Feature",
  "stac_version": "1.0.0",
  "id": "AZ30_1000_4509",
  "links": [
    { "rel": "self", "href": "./AZ30_1000_4509.json", "type": "application/json" },
    { "rel": "collection", "href": "./collection.json", "type": "application/json" },
    { "rel": "parent", "href": "./collection.json", "type": "application/json" }
  ],
  "assets": {
    "visual": {
      "href": "./AZ30_1000_4509.tiff",
      "type": "image/tiff; application=geotiff; profile=cloud-optimized",
      "file:checksum": "1220830edcbd296167520357e6c4d275b05af76f003b34a79b1fafb177c68d42075c"
    }
  },
  "stac_extensions": ["https://stac-extensions.github.io/file/v2.0.0/schema.json"],
  "properties": { "start_datetime": "2022-01-03T11:00:00Z", "end_datetime": "2022-02-14T11:00:00Z", "datetime": null },
  "geometry": {
    "type": "Polygon",
    "coordinates": [
      [
        [174.2501935, -36.5860457],
        [174.2502982, -36.592535],
        [174.2556631, -36.5924786],
        [174.255558, -36.5859893],
        [174.2501935, -36.5860457]
      ]
    ]
  },
  "bbox": [174.2501935, -36.592535, 174.2556631, -36.5859893],
  "collection": "01GSXJMK7G7Q6FWGZ6VK0Z0N9F"
}
