{
  "type": "Feature",
  "stac_version": "1.0.0",
  "id": "BW18_5000_0103",
  "links": [
    { "rel": "self", "href": "./BW18_5000_0103.json", "type": "application/json" },
    { "rel": "collection", "href": "./collection.json", "type": "application/json" },
    { "rel": "parent", "href": "./collection.json", "type": "application/json" }
  ],
  "assets": {
    "visual": {
      "href": "./BW18_5000_0103.tiff",
      "type": "image/tiff; application=geotiff; profile=cloud-optimized",
      "file:checksum": "12205bb8f5b8b3b9d6c6ae9422673a03ffc404e81bcdac3cd2ebbdf4747856cd1d98"
    }
  },
  "stac_extensions": ["https://stac-extensions.github.io/file/v2.0.0/schema.json"],
  "properties": { "start_datetime": "2017-02-07T11:00:00Z", "end_datetime": "2017-03-08T11:00:00Z", "datetime": null },
  "geometry": {
    "type": "Polygon",
    "coordinates": [
      [
        [170.8471201, -43.098476],
        [170.8459837, -43.1308707],
        [170.8754708, -43.1314223],
        [170.8765916, -43.0990269],
        [170.8471201, -43.098476]
      ]
    ]
  },
  "bbox": [170.8459837, -43.1314223, 170.8765916, -43.098476],
  "collection": "01GYBMMTT6BMHY041J2WTN6KG9"
}
