{
  "type": "Feature",
  "stac_version": "1.0.0",
  "id": "AV26_500_023046",
  "links": [
    { "rel": "self", "href": "./AV26_500_023046.json", "type": "application/json" },
    { "rel": "collection", "href": "./collection.json", "type": "application/json" },
    { "rel": "parent", "href": "./collection.json", "type": "application/json" }
  ],
  "assets": {
    "visual": {
      "href": "./AV26_500_023046.tiff",
      "type": "image/tiff; application=geotiff; profile=cloud-optimized",
      "file:checksum": "12201134641066b9e9564d1c0f9ca4ddd0e7701baa5cd07df45e088efc35a10eaadd"
    }
  },
  "stac_extensions": ["https://stac-extensions.github.io/file/v2.0.0/schema.json"],
  "properties": { "start_datetime": "2016-03-19T11:00:00Z", "end_datetime": "2016-07-01T12:00:00Z", "datetime": null },
  "geometry": {
    "type": "Polygon",
    "coordinates": [
      [
        [173.2501012, -35.0797888],
        [173.2501111, -35.083035],
        [173.2527439, -35.0830296],
        [173.2527339, -35.0797834],
        [173.2501012, -35.0797888]
      ]
    ]
  },
  "bbox": [173.2501012, -35.083035, 173.2527439, -35.0797834],
  "collection": "01GSTYRV1QJNS6ZNDA7F1W007G"
}
