{
  "type": "Feature",
  "stac_version": "1.0.0",
  "id": "BM35_1000_2021",
  "links": [
    { "rel": "self", "href": "./BM35_1000_2021.json", "type": "application/json" },
    { "rel": "collection", "href": "./collection.json", "type": "application/json" },
    { "rel": "parent", "href": "./collection.json", "type": "application/json" }
  ],
  "assets": {
    "visual": {
      "href": "./BM35_1000_2021.tiff",
      "type": "image/tiff; application=geotiff; profile=cloud-optimized",
      "file:checksum": "1220253b542609eb5c19900acd7b381274646997e4c1975b1db11951fdca53efa099"
    }
  },
  "stac_extensions": ["https://stac-extensions.github.io/file/v2.0.0/schema.json"],
  "properties": { "start_datetime": "2019-01-28T11:00:00Z", "end_datetime": "2019-02-02T11:00:00Z", "datetime": null },
  "geometry": {
    "type": "Polygon",
    "coordinates": [
      [
        [175.7951872, -40.2898683],
        [175.7954543, -40.2963473],
        [175.8010953, -40.2962107],
        [175.8008276, -40.2897318],
        [175.7951872, -40.2898683]
      ]
    ]
  },
  "bbox": [175.7951872, -40.2963473, 175.8010953, -40.2897318],
  "collection": "01GYC6EZFJRX8J6KJ1RK79CEYM"
}
