{
  "type": "Feature",
  "stac_version": "1.0.0",
  "id": "BX23_500_020086",
  "links": [
    { "rel": "self", "href": "./BX23_500_020086.json", "type": "application/json" },
    { "rel": "collection", "href": "./collection.json", "type": "application/json" },
    { "rel": "parent", "href": "./collection.json", "type": "application/json" }
  ],
  "assets": {
    "visual": {
      "href": "./BX23_500_020086.tiff",
      "type": "image/tiff; application=geotiff; profile=cloud-optimized",
      "file:checksum": "12202ff9facc33dc3dec9ce619b35e572dd4270135cfaab72a1ab85625565beb2972"
    }
  },
  "stac_extensions": ["https://stac-extensions.github.io/file/v2.0.0/schema.json"],
  "properties": { "start_datetime": "2018-11-04T11:00:00Z", "end_datetime": "2019-03-25T11:00:00Z", "datetime": null },
  "geometry": {
    "type": "Polygon",
    "coordinates": [
      [
        [172.5101422, -43.5034404],
        [172.510116, -43.5066818],
        [172.5130849, -43.5066945],
        [172.513111, -43.5034531],
        [172.5101422, -43.5034404]
      ]
    ]
  },
  "bbox": [172.510116, -43.5066945, 172.513111, -43.5034404],
  "collection": "01GSE3V417FCPJPMFTS74VBXZR"
}
