{
  "type": "Feature",
  "stac_version": "1.0.0",
  "id": "BX24_500_019005",
  "links": [
    { "rel": "self", "href": "./BX24_500_019005.json", "type": "application/json" },
    { "rel": "collection", "href": "./collection.json", "type": "application/json" },
    { "rel": "parent", "href": "./collection.json", "type": "application/json" }
  ],
  "assets": {
    "visual": {
      "href": "./BX24_500_019005.tiff",
      "type": "image/tiff; application=geotiff; profile=cloud-optimized",
      "file:checksum": "12203f1d3cf765e067f6ed01e539d664e0854c934ef7d437c06876c8b26382fab03b"
    }
  },
  "stac_extensions": ["https://stac-extensions.github.io/file/v2.0.0/schema.json"],
  "properties": { "start_datetime": "2018-11-04T11:00:00Z", "end_datetime": "2019-03-25T11:00:00Z", "datetime": null },
  "geometry": {
    "type": "Polygon",
    "coordinates": [
      [
        [172.5665716, -43.5004267],
        [172.5665484, -43.5036681],
        [172.5695172, -43.5036794],
        [172.5695402, -43.5004379],
        [172.5665716, -43.5004267]
      ]
    ]
  },
  "bbox": [172.5665484, -43.5036794, 172.5695402, -43.5004267],
  "collection": "01GSE3V417FCPJPMFTS74VBXZR"
}
