{
  "type": "Feature",
  "stac_version": "1.0.0",
  "id": "BY21_500_032041",
  "links": [
    { "rel": "self", "href": "./BY21_500_032041.json", "type": "application/json" },
    { "rel": "collection", "href": "./collection.json", "type": "application/json" },
    { "rel": "parent", "href": "./collection.json", "type": "application/json" }
  ],
  "assets": {
    "visual": {
      "href": "./BY21_500_032041.tiff",
      "type": "image/tiff; application=geotiff; profile=cloud-optimized",
      "file:checksum": "12201644472e4d3e38e9b30d5618e5b00d41a14a38a13e35e4bbf7db18a708f0f7cf"
    }
  },
  "stac_extensions": ["https://stac-extensions.github.io/file/v2.0.0/schema.json"],
  "properties": { "start_datetime": "2020-01-15T11:00:00Z", "end_datetime": "2020-01-16T11:00:00Z", "datetime": null },
  "geometry": {
    "type": "Polygon",
    "coordinates": [
      [
        [171.7755307, -43.860971],
        [171.7754643, -43.8642116],
        [171.7784503, -43.8642435],
        [171.7785165, -43.8610029],
        [171.7755307, -43.860971]
      ]
    ]
  },
  "bbox": [171.7754643, -43.8642435, 171.7785165, -43.860971],
  "collection": "01GSX8XMXSJC7SBN1DJPMCP69Q"
}
