{
  "type": "Feature",
  "stac_version": "1.0.0",
  "id": "BY21_500_046008",
  "links": [
    { "rel": "self", "href": "./BY21_500_046008.json", "type": "application/json" },
    { "rel": "collection", "href": "./collection.json", "type": "application/json" },
    { "rel": "parent", "href": "./collection.json", "type": "application/json" }
  ],
  "assets": {
    "visual": {
      "href": "./BY21_500_046008.tiff",
      "type": "image/tiff; application=geotiff; profile=cloud-optimized",
      "file:checksum": "1220630f56d3f1b428364eff6c6d9b1abbe8341e45b486e414b379823ee111aaa1df"
    }
  },
  "stac_extensions": ["https://stac-extensions.github.io/file/v2.0.0/schema.json"],
  "properties": { "start_datetime": "2020-01-15T11:00:00Z", "end_datetime": "2020-01-16T11:00:00Z", "datetime": null },
  "geometry": {
    "type": "Polygon",
    "coordinates": [
      [
        [171.6759963, -43.9052391],
        [171.6759245, -43.9084795],
        [171.6789126, -43.9085141],
        [171.6789842, -43.9052737],
        [171.6759963, -43.9052391]
      ]
    ]
  },
  "bbox": [171.6759245, -43.9085141, 171.6789842, -43.9052391],
  "collection": "01GSX8XMXSJC7SBN1DJPMCP69Q"
}
