{
  "type": "Feature",
  "stac_version": "1.0.0",
  "id": "BY21_500_008092",
  "links": [
    { "rel": "self", "href": "./BY21_500_008092.json", "type": "application/json" },
    { "rel": "collection", "href": "./collection.json", "type": "application/json" },
    { "rel": "parent", "href": "./collection.json", "type": "application/json" }
  ],
  "assets": {
    "visual": {
      "href": "./BY21_500_008092.tiff",
      "type": "image/tiff; application=geotiff; profile=cloud-optimized",
      "file:checksum": "122066cc93bb593edbc3c0e6acaaca691d19678070d7784a0d5f7b0a1b0c9b84f1af"
    }
  },
  "stac_extensions": ["https://stac-extensions.github.io/file/v2.0.0/schema.json"],
  "properties": { "start_datetime": "2020-01-15T11:00:00Z", "end_datetime": "2020-01-16T11:00:00Z", "datetime": null },
  "geometry": {
    "type": "Polygon",
    "coordinates": [
      [
        [171.9292058, -43.7847222],
        [171.9291479, -43.787963],
        [171.9321303, -43.787991],
        [171.932188, -43.7847501],
        [171.9292058, -43.7847222]
      ]
    ]
  },
  "bbox": [171.9291479, -43.787991, 171.932188, -43.7847222],
  "collection": "01GSX8XMXSJC7SBN1DJPMCP69Q"
}
