{
  "type": "Feature",
  "stac_version": "1.0.0",
  "id": "BE40_1000_1616",
  "links": [
    { "rel": "self", "href": "./BE40_1000_1616.json", "type": "application/json" },
    { "rel": "collection", "href": "./collection.json", "type": "application/json" },
    { "rel": "parent", "href": "./collection.json", "type": "application/json" }
  ],
  "assets": {
    "visual": {
      "href": "./BE40_1000_1616.tiff",
      "type": "image/tiff; application=geotiff; profile=cloud-optimized",
      "file:checksum": "1220971dda241c9d4266b56d0d75968e87bf245dbc763d24cb3d5d149179a914cc03"
    }
  },
  "stac_extensions": ["https://stac-extensions.github.io/file/v2.0.0/schema.json"],
  "properties": { "start_datetime": "2018-07-11T12:00:00Z", "end_datetime": "2019-01-16T11:00:00Z", "datetime": null },
  "geometry": {
    "type": "Polygon",
    "coordinates": [
      [
        [177.0425187, -37.9573731],
        [177.0428742, -37.9638462],
        [177.048325, -37.9636585],
        [177.0479691, -37.9571854],
        [177.0425187, -37.9573731]
      ]
    ]
  },
  "bbox": [177.0425187, -37.9638462, 177.048325, -37.9571854],
  "collection": "01GYC6EZJB6CJVZKFXHBHEWD2V"
}
