{
  "type": "Feature",
  "stac_version": "1.0.0",
  "id": "BS28_2000_0323",
  "links": [
    { "rel": "self", "href": "./BS28_2000_0323.json", "type": "application/json" },
    { "rel": "collection", "href": "./collection.json", "type": "application/json" },
    { "rel": "parent", "href": "./collection.json", "type": "application/json" }
  ],
  "assets": {
    "visual": {
      "href": "./BS28_2000_0323.tiff",
      "type": "image/tiff; application=geotiff; profile=cloud-optimized",
      "file:checksum": "1220598d3b45f0ffd8cfa7d0623abf1483bd4ceffd2528d517be6d8ffe7274ad46fb"
    }
  },
  "stac_extensions": ["https://stac-extensions.github.io/file/v2.0.0/schema.json"],
  "properties": { "start_datetime": "2021-11-07T11:00:00Z", "end_datetime": "2022-01-29T11:00:00Z", "datetime": null },
  "geometry": {
    "type": "Polygon",
    "coordinates": [
      [
        [173.9771083, -41.843663],
        [173.9773057, -41.856631],
        [173.9888698, -41.856532],
        [173.9886701, -41.843564],
        [173.9771083, -41.843663]
      ]
    ]
  },
  "bbox": [173.9771083, -41.856631, 173.9888698, -41.843564],
  "collection": "01GSXPM5P279P7KT5BNQC7HRW8"
}
