{
  "type": "Feature",
  "stac_version": "1.0.0",
  "id": "CG10_1000_4445",
  "links": [
    { "rel": "self", "href": "./CG10_1000_4445.json", "type": "application/json" },
    { "rel": "collection", "href": "./collection.json", "type": "application/json" },
    { "rel": "parent", "href": "./collection.json", "type": "application/json" }
  ],
  "assets": {
    "visual": {
      "href": "./CG10_1000_4445.tiff",
      "type": "image/tiff; application=geotiff; profile=cloud-optimized",
      "file:checksum": "1220d02ac75b37352670a9e2176d951da351bbef55920088e780dd6988da36cac01d"
    }
  },
  "stac_extensions": ["https://stac-extensions.github.io/file/v2.0.0/schema.json"],
  "properties": { "start_datetime": "2016-02-06T11:00:00Z", "end_datetime": "2016-02-06T11:00:00Z", "datetime": null },
  "geometry": {
    "type": "Polygon",
    "coordinates": [
      [
        [168.4230271, -46.5465481],
        [168.422483, -46.5530071],
        [168.4287247, -46.5532572],
        [168.429268, -46.5467982],
        [168.4230271, -46.5465481]
      ]
    ]
  },
  "bbox": [168.422483, -46.5532572, 168.429268, -46.5465481],
  "collection": "01GY9F9JMRKCSWNWYJ7T13MMB4"
}
