{
  "type": "Feature",
  "stac_version": "1.0.0",
  "id": "BN33_5000_0903",
  "links": [
    { "rel": "self", "href": "./BN33_5000_0903.json", "type": "application/json" },
    { "rel": "collection", "href": "./collection.json", "type": "application/json" },
    { "rel": "parent", "href": "./collection.json", "type": "application/json" }
  ],
  "assets": {
    "visual": {
      "href": "./BN33_5000_0903.tiff",
      "type": "image/tiff; application=geotiff; profile=cloud-optimized",
      "file:checksum": "122007b4cf44aa3228231fed1ad379805a57b4ebc7182fb8a98208f8fc26c69e365e"
    }
  },
  "stac_extensions": ["https://stac-extensions.github.io/file/v2.0.0/schema.json"],
  "properties": { "start_datetime": "2021-01-26T11:00:00Z", "end_datetime": "2022-07-03T12:00:00Z", "datetime": null },
  "geometry": {
    "type": "Polygon",
    "coordinates": [
      [
        [175.1894539, -40.7634106],
        [175.1905188, -40.7958178],
        [175.2189469, -40.7952744],
        [175.2178682, -40.7628678],
        [175.1894539, -40.7634106]
      ]
    ]
  },
  "bbox": [175.1894539, -40.7958178, 175.2189469, -40.7628678],
  "collection": "01GVC0V5HYNDWN3CBR34S53VBN"
}
