{
  "type": "Collection",
  "stac_version": "1.0.0",
  "id": "01KFVKRQS1W48KS0Z0XZFF1PXQ",
  "title": "Bay of Plenty 0.1m Urban Aerial Photos (2025) - Draft",
  "description": "Orthophotography within the Bay of Plenty region captured in the 2025 flying season.",
  "license": "CC-BY-4.0",
  "links": [
    {
      "rel": "root",
      "href": "https://nz-imagery.s3.ap-southeast-2.amazonaws.com/catalog.json",
      "type": "application/json"
    },
    { "rel": "self", "href": "./collection.json", "type": "application/json" },
    {
      "href": "./BD38_5000_0603.json",
      "rel": "item",
      "type": "application/geo+json",
      "file:checksum": "1220e2933ef4b6a0b25cd9c889ac84edfaa7a31b2e174940280dc7bc43b7b842c2cd"
    },
    {
      "href": "./BD38_5000_0703.json",
      "rel": "item",
      "type": "application/geo+json",
      "file:checksum": "1220466737ec08242615ea96ab0d1a20e12ff28168d35aeda3485abdbfe93686db79"
    },
    {
      "href": "./BD38_5000_0704.json",
      "rel": "item",
      "type": "application/geo+json",
      "file:checksum": "12208522058fcabb21db50db4656c840193398e716a13c8a3a7173e853ac3572ed99"
    },
    {
      "href": "./BD38_5000_0705.json",
      "rel": "item",
      "type": "application/geo+json",
      "file:checksum": "122007c0d8a607d0e43832387422766afb76e3120a966917cdd5da6201c6b71f625f"
    },
    {
      "href": "./BD38_5000_0804.json",
      "rel": "item",
      "type": "application/geo+json",
      "file:checksum": "12209f3d79280f7e431be10afff6c965edd5d73ba377f16eda63ef7cb9ca7ace41a1"
    },
    {
      "href": "./BD38_5000_0805.json",
      "rel": "item",
      "type": "application/geo+json",
      "file:checksum": "1220156fae3d14b8b8257f4990085c5e1190ebf9a9bb539d9cd3be74cae5ffb67228"
    },
    {
      "href": "./BD38_5000_0806.json",
      "rel": "item",
      "type": "application/geo+json",
      "file:checksum": "1220c7153e5a6623d6e0ff60be263d1ae8715f0ea3f90c2eee22dd384a91781448fc"
    },
    {
      "href": "./BD38_5000_0906.json",
      "rel": "item",
      "type": "application/geo+json",
      "file:checksum": "1220f2c1f097ad72783221c06fafaa1a650efc777bf4c58ccd726253026dbab39b62"
    },
    {
      "href": "./BD38_5000_0907.json",
      "rel": "item",
      "type": "application/geo+json",
      "file:checksum": "122005697641bea368242a2165ca1a60c293c94eb072f26cdd12850d90e250483959"
    },
    {
      "href": "./BD38_5000_0908.json",
      "rel": "item",
      "type": "application/geo+json",
      "file:checksum": "12201c226594da976caf729be8a8051e734fa721663392f544b2dd9dcd166045630e"
    },
    {
      "href": "./BD38_5000_0909.json",
      "rel": "item",
      "type": "application/geo+json",
      "file:checksum": "12204478a7a4ce4ee9f71342008c97c1af8a3813c6091c9c74caaf0dc26b410db64a"
    },
    {
      "href": "./BD38_5000_1008.json",
      "rel": "item",
      "type": "application/geo+json",
      "file:checksum": "12203e8f2526896b85a3f6aec749459c51203e360b6dcd0362ea5dae2231d12ded71"
    },
    {
      "href": "./BD38_5000_1009.json",
      "rel": "item",
      "type": "application/geo+json",
      "file:checksum": "122043826e326f9e2f814c865b29dba6aa10f7b0a625efed7c115efb2666b936b5f5"
    },
    {
      "href": "./BD38_5000_1010.json",
      "rel": "item",
      "type": "application/geo+json",
      "file:checksum": "1220c085044dd5bd528e7ea7ed852b8a32dd655701ef17c2d70d09cc774acf8b15d0"
    },
    {
      "href": "./BD39_5000_1001.json",
      "rel": "item",
      "type": "application/geo+json",
      "file:checksum": "1220e57cbe1691879313b8ff260e4a38aed110337a396893a3d4956fde9b14a2a3a2"
    },
    {
      "href": "./BD39_5000_1002.json",
      "rel": "item",
      "type": "application/geo+json",
      "file:checksum": "1220e80a2c94dcd53f3fc15ba7611b7283aa6c6387d45442405b2518dac88c96e67c"
    },
    {
      "href": "./BD42_5000_0609.json",
      "rel": "item",
      "type": "application/geo+json",
      "file:checksum": "1220eef7ea8bba69fb56553d8fc18b5c7b80c7c0fede80cfc70d58c39f98fa27b3c0"
    },
    {
      "href": "./BD42_5000_0610.json",
      "rel": "item",
      "type": "application/geo+json",
      "file:checksum": "12205c234c67962ca6a40497cb768ee172ffeb7100884f09c284a687cc6993f57cf2"
    },
    {
      "href": "./BD42_5000_0707.json",
      "rel": "item",
      "type": "application/geo+json",
      "file:checksum": "12203ae1f36b15aee25ec7c839ef15e66e52a8486278f440bac03aa252d07137c764"
    },
    {
      "href": "./BD42_5000_0708.json",
      "rel": "item",
      "type": "application/geo+json",
      "file:checksum": "12207ad4a9d257db299405b88e619ea22e84139e7df4b61e76e304e9fb6f2b38f7e3"
    },
    {
      "href": "./BD42_5000_0709.json",
      "rel": "item",
      "type": "application/geo+json",
      "file:checksum": "12206cd16a42d2f210c5fc80190281157232980c796015d7235e8b906964c251fac8"
    },
    {
      "href": "./BD42_5000_0807.json",
      "rel": "item",
      "type": "application/geo+json",
      "file:checksum": "122074bb46442f50d4166319659f5c9e01d66597f034d4ce8d7666448b99a7a6db7f"
    },
    {
      "href": "./BD42_5000_0808.json",
      "rel": "item",
      "type": "application/geo+json",
      "file:checksum": "1220ef8965b30bba9c2f7867d8a2b6257c3b4d7a4e3b93deee1503727353c6f91c47"
    },
    {
      "href": "./BD42_5000_0906.json",
      "rel": "item",
      "type": "application/geo+json",
      "file:checksum": "122025d9fb7e94692a2de70b11a8211134a8f8a46655f13932cc96cc17ffa1cfcf9d"
    },
    {
      "href": "./BD42_5000_0907.json",
      "rel": "item",
      "type": "application/geo+json",
      "file:checksum": "12208cea4996b99d6068655e2343db29b6ed85abd7ff1a03d6692670c9da612c13d7"
    },
    {
      "href": "./BD42_5000_1004.json",
      "rel": "item",
      "type": "application/geo+json",
      "file:checksum": "1220e5ecdbd632f656e261b5ce788a18a39359b07e49ad7e8aaaeecb9a8212c7f20d"
    },
    {
      "href": "./BD42_5000_1005.json",
      "rel": "item",
      "type": "application/geo+json",
      "file:checksum": "1220c6302937a2f24cb493eeea3630846791b1735748fac630b8f64313748b0f6d43"
    },
    {
      "href": "./BD42_5000_1006.json",
      "rel": "item",
      "type": "application/geo+json",
      "file:checksum": "1220a15c1fdf00d3cb7e88028c5755f98c4d69d6a6cf374ab373337ac72c3846a775"
    },
    {
      "href": "./BD43_5000_0109.json",
      "rel": "item",
      "type": "application/geo+json",
      "file:checksum": "1220770731f54f7c7dc8ca12e6084aa2dafaaaaba34f4c77880738a2e43901423e6e"
    },
    {
      "href": "./BD43_5000_0209.json",
      "rel": "item",
      "type": "application/geo+json",
      "file:checksum": "1220a8d4002251102bf7e9ddf80536132efea99307f9c873fa7e3c204ddd4f8f1964"
    },
    {
      "href": "./BD43_5000_0210.json",
      "rel": "item",
      "type": "application/geo+json",
      "file:checksum": "12204c3bd545b9f47c80f6a9db961f73f2b1e81aa22f341c8ccbc0b846858dbed902"
    },
    {
      "href": "./BD43_5000_0308.json",
      "rel": "item",
      "type": "application/geo+json",
      "file:checksum": "12203ccc5cac914452448bae90359bc7b4a25a70b0ce87aa1066eda48ca348f12c1e"
    },
    {
      "href": "./BD43_5000_0309.json",
      "rel": "item",
      "type": "application/geo+json",
      "file:checksum": "1220b3990f476d992faf57d6d7115aa86aefb22ff1c436fd30ba40d619ceb5cc2377"
    },
    {
      "href": "./BD43_5000_0310.json",
      "rel": "item",
      "type": "application/geo+json",
      "file:checksum": "1220382fded72f3a2971562572118914bef02ecc0f82e975d472278d1b13532eebf4"
    },
    {
      "href": "./BD43_5000_0405.json",
      "rel": "item",
      "type": "application/geo+json",
      "file:checksum": "12208be838e3039586cf33438953ed372bd705c4ac381d3616a5bc8cfc8a811dbb79"
    },
    {
      "href": "./BD43_5000_0406.json",
      "rel": "item",
      "type": "application/geo+json",
      "file:checksum": "1220a7b891427f1c8e3f082c959f52b2626accb8a81185e8788d2a63aea4f67fed86"
    },
    {
      "href": "./BD43_5000_0407.json",
      "rel": "item",
      "type": "application/geo+json",
      "file:checksum": "1220e52f17d37a2eeaf6ea8db31311b6574edb9f96ece76451175b10a6fe55904f26"
    },
    {
      "href": "./BD43_5000_0408.json",
      "rel": "item",
      "type": "application/geo+json",
      "file:checksum": "122041c497ae132bbe2a361e9822ad5542daa9b76ba3153bfcb38ab2316008f683b1"
    },
    {
      "href": "./BD43_5000_0502.json",
      "rel": "item",
      "type": "application/geo+json",
      "file:checksum": "12202f45a7908f8285dec60a113f9ce2e64d3b9b76658432ce7c5df0f9ffc706de60"
    },
    {
      "href": "./BD43_5000_0503.json",
      "rel": "item",
      "type": "application/geo+json",
      "file:checksum": "12200280e8b39c49f8bd02b417c5a5b9edb751f54523d1bd4ec5996c79f1fc55c3a5"
    },
    {
      "href": "./BD43_5000_0504.json",
      "rel": "item",
      "type": "application/geo+json",
      "file:checksum": "122042fc66acd99794d015ddb5815be15d07395f8e20bd38d5c131af4203bc9e0eed"
    },
    {
      "href": "./BD43_5000_0505.json",
      "rel": "item",
      "type": "application/geo+json",
      "file:checksum": "1220396f2295537751a95283013e4923324165aeb1c60b54e9689fcf520f02775407"
    },
    {
      "href": "./BD43_5000_0601.json",
      "rel": "item",
      "type": "application/geo+json",
      "file:checksum": "1220d8e81000ce74c694e0b31bdbea8bc46d18bc5eb1cbf02bd7906bb93daf0a8c6b"
    },
    {
      "href": "./BD43_5000_0602.json",
      "rel": "item",
      "type": "application/geo+json",
      "file:checksum": "122075ec2db6db9f0d1e32d64925dd8c5cbd9c710ef4111daa713a1dec582c020917"
    },
    {
      "href": "./BD44_5000_0201.json",
      "rel": "item",
      "type": "application/geo+json",
      "file:checksum": "122002b673217584af905518320dcafe2a733960112a308f04021f4b224b06202a0f"
    },
    {
      "href": "./BD44_5000_0202.json",
      "rel": "item",
      "type": "application/geo+json",
      "file:checksum": "1220f63763eeaead42033f870610f0c068496aec4d2e6ae55245f0f5df5b649e5f20"
    },
    {
      "href": "./BD44_5000_0203.json",
      "rel": "item",
      "type": "application/geo+json",
      "file:checksum": "1220731b9e0fa546410dde96076e58b6a36120bca702c8fb0670eb0b57825167acb8"
    },
    {
      "href": "./BE36_5000_0210.json",
      "rel": "item",
      "type": "application/geo+json",
      "file:checksum": "122007fe7d5147927b861ebce36a1e47d62bd381cb065d0e12e2861a12e08a283cda"
    },
    {
      "href": "./BE36_5000_0310.json",
      "rel": "item",
      "type": "application/geo+json",
      "file:checksum": "12204725db648f89651f169962aa4d32c215ae5d98b358b0bc8fb666e1f7966d366d"
    },
    {
      "href": "./BE36_5000_0608.json",
      "rel": "item",
      "type": "application/geo+json",
      "file:checksum": "1220e82d6fc9d9b67026bf9c55150e6d73bc4e0cc260567219ff88914837fdebe41e"
    },
    {
      "href": "./BE36_5000_0708.json",
      "rel": "item",
      "type": "application/geo+json",
      "file:checksum": "12207abb26cfe3d92e371dd4e4daa2e1e8a0f9284cc97791c0a59e4d9b9b8d3ba1b1"
    },
    {
      "href": "./BE37_5000_0101.json",
      "rel": "item",
      "type": "application/geo+json",
      "file:checksum": "122043610e31defe5ea0c2f7afbca1fa3dfbaf887c9c5b781728bea2948735222616"
    },
    {
      "href": "./BE37_5000_0201.json",
      "rel": "item",
      "type": "application/geo+json",
      "file:checksum": "12202dec40f573178cfa7ccb7ecdc9487cd9c1c1b7f2cb21081cb269b3d73a965037"
    },
    {
      "href": "./BE37_5000_0202.json",
      "rel": "item",
      "type": "application/geo+json",
      "file:checksum": "12200bc9383556bb0d2d4d45e947174a16f9439d00372ce16e52f47a29633e3d69ad"
    },
    {
      "href": "./BE37_5000_0301.json",
      "rel": "item",
      "type": "application/geo+json",
      "file:checksum": "12208010aabfc3c53202a755dce1c10eb112f7e04109ebf6f05c429220b3e4e8deec"
    },
    {
      "href": "./BE37_5000_0302.json",
      "rel": "item",
      "type": "application/geo+json",
      "file:checksum": "1220719339c4e57fa0bf8b4c5b8b4fdcec0753efe93761db03c917f9a977615f5069"
    },
    {
      "href": "./BE37_5000_0408.json",
      "rel": "item",
      "type": "application/geo+json",
      "file:checksum": "122003555cca810ba7b0f613fe4a359ee94621fd53647abaea958be35803990cd83b"
    },
    {
      "href": "./BE37_5000_0409.json",
      "rel": "item",
      "type": "application/geo+json",
      "file:checksum": "12207ac54e556f6a3face35b0d0ffd0306a6c95e783ef3d53b95f81ef81fde5b0f8d"
    },
    {
      "href": "./BE37_5000_0502.json",
      "rel": "item",
      "type": "application/geo+json",
      "file:checksum": "12205f51c7ac81e629594634773bc86d3e2e0c949d3ddd718c56533b41d8b08cb86a"
    },
    {
      "href": "./BE37_5000_0503.json",
      "rel": "item",
      "type": "application/geo+json",
      "file:checksum": "12202e8b8a2164dc52a420602b5fe682369b2e4f347b6e163dce1c9c99966e2278c7"
    },
    {
      "href": "./BE37_5000_0504.json",
      "rel": "item",
      "type": "application/geo+json",
      "file:checksum": "12205f9735e188d7093c7c868e685a94e07bede6a3617990b3cddedbf9b7f8fc1565"
    },
    {
      "href": "./BE37_5000_0505.json",
      "rel": "item",
      "type": "application/geo+json",
      "file:checksum": "12208034c8ae6882bd224b41df2e914f0b40424162adb963d04a9b23be41ca4c327a"
    },
    {
      "href": "./BE37_5000_0506.json",
      "rel": "item",
      "type": "application/geo+json",
      "file:checksum": "12204ecf7d8397508a277ec591b0c73725cf0ce36bfdb29c74e8e976362589108e13"
    },
    {
      "href": "./BE37_5000_0507.json",
      "rel": "item",
      "type": "application/geo+json",
      "file:checksum": "1220e2a3a69dfce85e07d9a15536d6047f0fda0acc300917697b4770b4512968373f"
    },
    {
      "href": "./BE37_5000_0508.json",
      "rel": "item",
      "type": "application/geo+json",
      "file:checksum": "1220a344046a8b352353108df2bf8da8f335b1c066a9fc22269734cdf1f8f62e9b4b"
    },
    {
      "href": "./BE37_5000_0509.json",
      "rel": "item",
      "type": "application/geo+json",
      "file:checksum": "12200a9f325377801209eda30e82cf30c81ec927e9d98ebd1294b2a90146a5d62928"
    },
    {
      "href": "./BE37_5000_0510.json",
      "rel": "item",
      "type": "application/geo+json",
      "file:checksum": "12208cc7ca4549a2b387e393ceba08737f143f3dbcd0c8e6a8cd84e207b480096c2b"
    },
    {
      "href": "./BE37_5000_0602.json",
      "rel": "item",
      "type": "application/geo+json",
      "file:checksum": "1220451553d89b02c925689f521fdbc5cd21dc41d428a6927fcee8985eede29c6223"
    },
    {
      "href": "./BE37_5000_0603.json",
      "rel": "item",
      "type": "application/geo+json",
      "file:checksum": "1220522a3144324f67ad24bdf3fc8987fed8ae3556b2ea2ad00eeb96b4300733f95b"
    },
    {
      "href": "./BE37_5000_0605.json",
      "rel": "item",
      "type": "application/geo+json",
      "file:checksum": "12200bd3d885101968714dc2c2e312199ee38f48510bd82417019d9b38de136707e5"
    },
    {
      "href": "./BE37_5000_0606.json",
      "rel": "item",
      "type": "application/geo+json",
      "file:checksum": "122059c41a6d0a1c8174f9caf6102f9d691317b0fe0ad709f6758e4ad560646fbc3a"
    },
    {
      "href": "./BE37_5000_0607.json",
      "rel": "item",
      "type": "application/geo+json",
      "file:checksum": "1220c2425df6a7379df797ec0af5f98a2a0f9ea2d016a39816891ad3eaa55516739b"
    },
    {
      "href": "./BE37_5000_0608.json",
      "rel": "item",
      "type": "application/geo+json",
      "file:checksum": "12202c422668b4b3c5f81d2f75c6aa72fc5ad9c1a5484871f809746db3966c33cceb"
    },
    {
      "href": "./BE37_5000_0610.json",
      "rel": "item",
      "type": "application/geo+json",
      "file:checksum": "122072ffa7a41172461d2bde426b5c1234ad0697342acd2ba5ca3464f78628ade1dd"
    },
    {
      "href": "./BE37_5000_0702.json",
      "rel": "item",
      "type": "application/geo+json",
      "file:checksum": "1220a538ae932269e67f36e2ef8346710cf236ff853d46e369a90dc4dabcb4b2466e"
    },
    {
      "href": "./BE37_5000_0703.json",
      "rel": "item",
      "type": "application/geo+json",
      "file:checksum": "12202ca5b64e4dee758b00e7d731208c32c0769251a1b96afbc8f66681d1204e9f30"
    },
    {
      "href": "./BE37_5000_0704.json",
      "rel": "item",
      "type": "application/geo+json",
      "file:checksum": "122068b3a5ed3c3fcdfaba807de51f4410fc4bab4a2d2a3d5002ff1b38db6edf7095"
    },
    {
      "href": "./BE37_5000_0705.json",
      "rel": "item",
      "type": "application/geo+json",
      "file:checksum": "122054a1d22cb7fef39b13301a38b83f26067b695e9379d2f67ddb2851c446bb34d9"
    },
    {
      "href": "./BE37_5000_0706.json",
      "rel": "item",
      "type": "application/geo+json",
      "file:checksum": "1220bde8bd45354359a461c918c859ac79f66c6d99a9c5650f70497a4803ec0c70b4"
    },
    {
      "href": "./BE37_5000_0707.json",
      "rel": "item",
      "type": "application/geo+json",
      "file:checksum": "12206d7e6e2fef9dec346d23ea15f102cd2dd166d5609b997696392986abc2cbbd25"
    },
    {
      "href": "./BE37_5000_0708.json",
      "rel": "item",
      "type": "application/geo+json",
      "file:checksum": "1220aafbd9b655dc711840c717caf1c48ae47c8a5c811157a0abdfd3515d79f12ba7"
    },
    {
      "href": "./BE37_5000_0802.json",
      "rel": "item",
      "type": "application/geo+json",
      "file:checksum": "122077f68cd2f5750ac590a29c90b98fd503c34493db3989e6482237da57ac998dc9"
    },
    {
      "href": "./BE37_5000_0803.json",
      "rel": "item",
      "type": "application/geo+json",
      "file:checksum": "1220dafa182452e2231b3618fc5239fc0ca10b9bcd0e67acb76e5643b0d7e1547ba0"
    },
    {
      "href": "./BE37_5000_0804.json",
      "rel": "item",
      "type": "application/geo+json",
      "file:checksum": "1220b736adfb91021dc66b33b6f29be62bf4af7cd7774e4f41aaa2d5b1e1a3eacb74"
    },
    {
      "href": "./BE37_5000_0805.json",
      "rel": "item",
      "type": "application/geo+json",
      "file:checksum": "122047677b84ec7104f3e651c99dfe3a225904b8c0adfa8f487db04f5391e927a18d"
    },
    {
      "href": "./BE37_5000_0806.json",
      "rel": "item",
      "type": "application/geo+json",
      "file:checksum": "1220a6bb5d88e38c4cdbb76fccdb00adf4704eb7cf51f32407830026d167e860f675"
    },
    {
      "href": "./BE37_5000_0807.json",
      "rel": "item",
      "type": "application/geo+json",
      "file:checksum": "1220fc73e84836b9f60040b204b98e7a8d8618ce24cfc5afe41bbe89067f09df3029"
    },
    {
      "href": "./BE37_5000_0902.json",
      "rel": "item",
      "type": "application/geo+json",
      "file:checksum": "12208e04b27f96ce42c79e5973c2bd0d9870f44c3b59a0d6749099cc5a4dadebaa7c"
    },
    {
      "href": "./BE37_5000_0903.json",
      "rel": "item",
      "type": "application/geo+json",
      "file:checksum": "12209fefa4a1749b62c61954e5a7426132baed5fb2de0090a21daa8486e6528ee648"
    },
    {
      "href": "./BE37_5000_0904.json",
      "rel": "item",
      "type": "application/geo+json",
      "file:checksum": "1220bd73553537aac08663474deefe49689f496b76ca28db4c3f5e72ec31dc86ee15"
    },
    {
      "href": "./BE37_5000_0905.json",
      "rel": "item",
      "type": "application/geo+json",
      "file:checksum": "122016be2de1a15886bfbe26e60e6b8fbc6eaccd999c983ab7bb6d3bec90db5bd090"
    },
    {
      "href": "./BE37_5000_0906.json",
      "rel": "item",
      "type": "application/geo+json",
      "file:checksum": "1220e1c4de528c0a6d7eb9edba1a0cf45f5f4da6ba824f3dbb690866a09a5593ffcb"
    },
    {
      "href": "./BE37_5000_0907.json",
      "rel": "item",
      "type": "application/geo+json",
      "file:checksum": "12204b2985381a71cf049815cc1b2dea986281066f177e04d8c3872895ed1732e9af"
    },
    {
      "href": "./BE37_5000_0908.json",
      "rel": "item",
      "type": "application/geo+json",
      "file:checksum": "12205ab2ad7b4255d60c42076b8d25a5d5088ebb9fa9ac6f306f6f34e7383e6b890c"
    },
    {
      "href": "./BE37_5000_0909.json",
      "rel": "item",
      "type": "application/geo+json",
      "file:checksum": "1220b7005215f5c9b934e2aac1b601ffd24e4d7c4ad7ca35bbcbdb72a3dfffab5365"
    },
    {
      "href": "./BE37_5000_0910.json",
      "rel": "item",
      "type": "application/geo+json",
      "file:checksum": "12208e0836d13af6faddb59d8bc20c719ec70989904a0b010f3c0938aa2da24ac4e3"
    },
    {
      "href": "./BE37_5000_1003.json",
      "rel": "item",
      "type": "application/geo+json",
      "file:checksum": "122067de9b3686ee7fc71ae160be9f91a35597ecccd3aff986660a9cc4159c6268f2"
    },
    {
      "href": "./BE37_5000_1004.json",
      "rel": "item",
      "type": "application/geo+json",
      "file:checksum": "1220db2e2f1707501f4f16667b55682f7a87f91be1f25622c6bd8262aa45c0119d21"
    },
    {
      "href": "./BE37_5000_1005.json",
      "rel": "item",
      "type": "application/geo+json",
      "file:checksum": "12202f4d4a44040673cddb18ccf7d38b28097be2b5c91debb96e290f9b4308ba3259"
    },
    {
      "href": "./BE37_5000_1006.json",
      "rel": "item",
      "type": "application/geo+json",
      "file:checksum": "1220afb605c25c4ec1cf911f227d5ee6201237f9a177712f23699559f663aa593024"
    },
    {
      "href": "./BE37_5000_1007.json",
      "rel": "item",
      "type": "application/geo+json",
      "file:checksum": "12206eb63f42398f4bf5999f6c5dbc401e8c59418cc2187292a75d4e28719d76b3a0"
    },
    {
      "href": "./BE37_5000_1008.json",
      "rel": "item",
      "type": "application/geo+json",
      "file:checksum": "12202ab3b73df1b042ee5404fd22d0513dd73596e5dfc4d04e5eb602f7e2ac076566"
    },
    {
      "href": "./BE37_5000_1009.json",
      "rel": "item",
      "type": "application/geo+json",
      "file:checksum": "122054884b249488e342952cfbdceb063b36634a3fe8d0fc4f9d2b0d4e0d2e63cc22"
    },
    {
      "href": "./BE38_5000_0503.json",
      "rel": "item",
      "type": "application/geo+json",
      "file:checksum": "1220cea65939e733bbee3a5bf8c6eae0c4fca70338bd412d5bf6482d81cef9ae3b95"
    },
    {
      "href": "./BE38_5000_0505.json",
      "rel": "item",
      "type": "application/geo+json",
      "file:checksum": "1220bdb312a08a0585685feac750d9b80d28fc199c3094477fc6309ef6018ebf35e8"
    },
    {
      "href": "./BE38_5000_0601.json",
      "rel": "item",
      "type": "application/geo+json",
      "file:checksum": "12209621dcb3a9c93614d6be9e7bdbbf29aaaffcb2dcb164ef81794718ca3d3a9f25"
    },
    {
      "href": "./BE38_5000_0602.json",
      "rel": "item",
      "type": "application/geo+json",
      "file:checksum": "12208ba9271d3cf7a3440f1114e52fa3617d6e5cd6a57e3610fa4938d602b5fad66c"
    },
    {
      "href": "./BE38_5000_0603.json",
      "rel": "item",
      "type": "application/geo+json",
      "file:checksum": "1220bdd22670aa5b0846b7ef1609c5447d256909bbf1be4136e9f84189b2bfd2ab9e"
    },
    {
      "href": "./BE38_5000_0605.json",
      "rel": "item",
      "type": "application/geo+json",
      "file:checksum": "1220830974b6e2fd8b19817da01cdeb9c268132deb4ecb571881ebb775254d2d441c"
    },
    {
      "href": "./BE38_5000_0606.json",
      "rel": "item",
      "type": "application/geo+json",
      "file:checksum": "122097c07a362a8a6b1286f03c23eedbf4d524f13cac1a0598ce5648980cad9a5088"
    },
    {
      "href": "./BE38_5000_0607.json",
      "rel": "item",
      "type": "application/geo+json",
      "file:checksum": "1220ddb4716396903c1f89f701f61edb26b7af328b0ad1227c1fdf1c063ef2767b6b"
    },
    {
      "href": "./BE38_5000_0707.json",
      "rel": "item",
      "type": "application/geo+json",
      "file:checksum": "122059ea6708a64f5058b18166824d7c5f822ece900ba650a6196f190c3e7ef949dc"
    },
    {
      "href": "./BE38_5000_0710.json",
      "rel": "item",
      "type": "application/geo+json",
      "file:checksum": "122049e67edbe702e747e84a75fb98f008ad394d083ae7b48f2280300e939d882044"
    },
    {
      "href": "./BE38_5000_0809.json",
      "rel": "item",
      "type": "application/geo+json",
      "file:checksum": "1220030e2a221befc5c17b0c168427fc2f01842fc5586c7a9e0959bc75dac9c68089"
    },
    {
      "href": "./BE38_5000_0810.json",
      "rel": "item",
      "type": "application/geo+json",
      "file:checksum": "12204a3562261ea87f05187e910154cece79c822ed75e9c8720081e531688ecae2a3"
    },
    {
      "href": "./BE38_5000_0904.json",
      "rel": "item",
      "type": "application/geo+json",
      "file:checksum": "12207d795cda29f26eb03b7b2f4a21a95ffebf3d390f83a21044dbf743bbf0223115"
    },
    {
      "href": "./BE38_5000_0905.json",
      "rel": "item",
      "type": "application/geo+json",
      "file:checksum": "12204a7d11a93cbc01fa784f4b0a13a9a12c74c34298fee1051721a90a1d605f98eb"
    },
    {
      "href": "./BE38_5000_0906.json",
      "rel": "item",
      "type": "application/geo+json",
      "file:checksum": "12205fc338fb229c4604bff484e255944308736716097276cb87d1d92d3864abc33f"
    },
    {
      "href": "./BE38_5000_0907.json",
      "rel": "item",
      "type": "application/geo+json",
      "file:checksum": "1220af709e86554aa5ac6f56d06732fe930ff1b3b7763941e3caf7b638264bb6fe78"
    },
    {
      "href": "./BE38_5000_0908.json",
      "rel": "item",
      "type": "application/geo+json",
      "file:checksum": "1220c211a91126af52688904233eb14327557bcb28b7cb5d16c2d3dc582227cccfc8"
    },
    {
      "href": "./BE38_5000_0909.json",
      "rel": "item",
      "type": "application/geo+json",
      "file:checksum": "12205d020e638a53f82f5c56597294b948634f2d5f0fbf9350df5164ea105fb8f234"
    },
    {
      "href": "./BE38_5000_1003.json",
      "rel": "item",
      "type": "application/geo+json",
      "file:checksum": "1220ae7d2ff8b5dba993208d422f8e79bbd65d3077a12f019ba6067fb14e1354db34"
    },
    {
      "href": "./BE38_5000_1004.json",
      "rel": "item",
      "type": "application/geo+json",
      "file:checksum": "1220482182b155d333edf7c205c6f8ce68845e2a4aae0176e8516663a857b0963167"
    },
    {
      "href": "./BE39_5000_0101.json",
      "rel": "item",
      "type": "application/geo+json",
      "file:checksum": "122051f537e2889645ec6eb912470cfd32b63a857b9a5a0db951f7e5216c7b0a4a93"
    },
    {
      "href": "./BE39_5000_0102.json",
      "rel": "item",
      "type": "application/geo+json",
      "file:checksum": "12209d0e60cfbb9ac534c2a09ec94248f8de17e6058a208b001d1b3b96d4a27ed17e"
    },
    {
      "href": "./BE39_5000_0103.json",
      "rel": "item",
      "type": "application/geo+json",
      "file:checksum": "12206031aaabc0a37ae6a4658ee09f917139d7fe3eb9a3e344257bdb4573091ccc32"
    },
    {
      "href": "./BE39_5000_0104.json",
      "rel": "item",
      "type": "application/geo+json",
      "file:checksum": "12201c24aa04658a16adbcce39029849058749a147a6d2d91462fa1a812e87c51b84"
    },
    {
      "href": "./BE39_5000_0105.json",
      "rel": "item",
      "type": "application/geo+json",
      "file:checksum": "12209b0e3272360651318601eab0bfccedff36ab67cc4982891ca7858621a76524da"
    },
    {
      "href": "./BE39_5000_0106.json",
      "rel": "item",
      "type": "application/geo+json",
      "file:checksum": "122005ec4b91619a2c8e8fce1140538885d27f803bef034021a9841c76155981547e"
    },
    {
      "href": "./BE39_5000_0203.json",
      "rel": "item",
      "type": "application/geo+json",
      "file:checksum": "12208901f118f7743965d7ef5926ee3d0b90c641bc47611f8de6f9f672573d3ef29d"
    },
    {
      "href": "./BE39_5000_0205.json",
      "rel": "item",
      "type": "application/geo+json",
      "file:checksum": "1220d64cabef1c97a16f5e2fc51e989d36db6ef291c78db03aa59c6cc71972aea92c"
    },
    {
      "href": "./BE39_5000_0206.json",
      "rel": "item",
      "type": "application/geo+json",
      "file:checksum": "1220dd393a1b5a67e13b71a2109c64983ab634f3ea3840bb36efb5be6af9df107aa0"
    },
    {
      "href": "./BE39_5000_0207.json",
      "rel": "item",
      "type": "application/geo+json",
      "file:checksum": "122080f60c65b7b9ac227852589aa0a4fa5c0f1693d148dadc50e756a2cbbe5fee51"
    },
    {
      "href": "./BE39_5000_0208.json",
      "rel": "item",
      "type": "application/geo+json",
      "file:checksum": "12201fca041b5f14e32e91305561b2cf59e276bf1cd8eabf62f0b69ba994262f474d"
    },
    {
      "href": "./BE39_5000_0209.json",
      "rel": "item",
      "type": "application/geo+json",
      "file:checksum": "1220eecbef32a23489800c255c2db838dd59109e22c86398c31baacc0fc4ec6c4f54"
    },
    {
      "href": "./BE39_5000_0210.json",
      "rel": "item",
      "type": "application/geo+json",
      "file:checksum": "12204aa2f815c9dd69d12d590ccfa2aa2cf09c2685b41092cd720fefb37dcdb72736"
    },
    {
      "href": "./BE39_5000_0305.json",
      "rel": "item",
      "type": "application/geo+json",
      "file:checksum": "1220f13643aa3c9b102ea95e57264203e691a20b798e4c9e10cdc3e6d495e39e1ba4"
    },
    {
      "href": "./BE39_5000_0306.json",
      "rel": "item",
      "type": "application/geo+json",
      "file:checksum": "12209806bc92773bc1d8b246cca868eba4ccd7debc35ab839b72905ba8a9beedf9ee"
    },
    {
      "href": "./BE39_5000_0309.json",
      "rel": "item",
      "type": "application/geo+json",
      "file:checksum": "12209bccd5f2d1858e5bcb9148cbc18c0964604f99a802406c4ecc668374c233076c"
    },
    {
      "href": "./BE39_5000_0310.json",
      "rel": "item",
      "type": "application/geo+json",
      "file:checksum": "1220981a58bbf83b24f14f91f58aa55aa962cd46f0f12069d3e33be6e42bf6c3f715"
    },
    {
      "href": "./BE39_5000_0405.json",
      "rel": "item",
      "type": "application/geo+json",
      "file:checksum": "1220c153d4af505b2d1b43c62f18a7ef6f83a57618e2d9bb4d71410db20e679efde5"
    },
    {
      "href": "./BE39_5000_0406.json",
      "rel": "item",
      "type": "application/geo+json",
      "file:checksum": "12205254e3b87ae99b7559d3c3bcf7fe005997fd4d6545c79f46d2fe5b5d26c40bc5"
    },
    {
      "href": "./BE39_5000_0410.json",
      "rel": "item",
      "type": "application/geo+json",
      "file:checksum": "1220c98cc4f9b66827e01ded14ca158dbbb30a5cb07d1e9c68e4785a9e8160ff758a"
    },
    {
      "href": "./BE39_5000_0601.json",
      "rel": "item",
      "type": "application/geo+json",
      "file:checksum": "1220e7962645d4817d4509e1932c15bdae4e03237a9865f31cf92ca271864317f090"
    },
    {
      "href": "./BE39_5000_0602.json",
      "rel": "item",
      "type": "application/geo+json",
      "file:checksum": "12207a670900335ad6356a197e1fe68d8a5bb467c62c06949fcc3e8eaffff79b0cba"
    },
    {
      "href": "./BE39_5000_0701.json",
      "rel": "item",
      "type": "application/geo+json",
      "file:checksum": "12207554f8f735bee2712e36ea6ded41ac0ccb4c6322bc6d125fcd17f9de6c8a208e"
    },
    {
      "href": "./BE39_5000_0702.json",
      "rel": "item",
      "type": "application/geo+json",
      "file:checksum": "1220a9811764c7786b9e2d97de871593a83ccce3a8c6f709da264276e7b155f80e9f"
    },
    {
      "href": "./BE39_5000_0801.json",
      "rel": "item",
      "type": "application/geo+json",
      "file:checksum": "1220dbedb8087baae97d930ebc7096cf377241ecd19d1a6dde0d093ff40588ab9081"
    },
    {
      "href": "./BE39_5000_0802.json",
      "rel": "item",
      "type": "application/geo+json",
      "file:checksum": "1220a28f2d65c97802c1ff7af7d03e7406953fddf026fce480d5c410e9c96f19f568"
    },
    {
      "href": "./BE39_5000_0803.json",
      "rel": "item",
      "type": "application/geo+json",
      "file:checksum": "1220c07fe7017eebcaa5f61b38777f64160e89dfbbaee327f86137c9a678e8bbbc49"
    },
    {
      "href": "./BE40_5000_0201.json",
      "rel": "item",
      "type": "application/geo+json",
      "file:checksum": "1220c605a4f7c53018fa26b0724711ab1ea2993a82b3eb77a874ac64e8493e3a923c"
    },
    {
      "href": "./BE40_5000_0301.json",
      "rel": "item",
      "type": "application/geo+json",
      "file:checksum": "1220e14dbfe2aab93afb9225973bd8846f5f464154546cb1ab3a435db089f4c0ac89"
    },
    {
      "href": "./BE40_5000_0302.json",
      "rel": "item",
      "type": "application/geo+json",
      "file:checksum": "12209875b7a7c61aa214d0757fd8528f2c3d1cf80c703b98c4d5df2288618a94b03f"
    },
    {
      "href": "./BE40_5000_0303.json",
      "rel": "item",
      "type": "application/geo+json",
      "file:checksum": "1220015b048265c29307096aa7e51f68f72c30698372174ffd1ebcc3b48fde5c16f2"
    },
    {
      "href": "./BE40_5000_0401.json",
      "rel": "item",
      "type": "application/geo+json",
      "file:checksum": "1220dbc7189ebdb86af7adb8daffb6cde6ff80a5c644936ddf5c69a0c7f4dbf574f5"
    },
    {
      "href": "./BE40_5000_0402.json",
      "rel": "item",
      "type": "application/geo+json",
      "file:checksum": "1220afd5a8a9339e7a91bac400448d7a8e8ccc1b53c0183813b5441353d366b417d0"
    },
    {
      "href": "./BE40_5000_0403.json",
      "rel": "item",
      "type": "application/geo+json",
      "file:checksum": "122057e2206085a4cafdcc1fa934942284d960e74090679358f181dd28623f04e6bc"
    },
    {
      "href": "./BE40_5000_0404.json",
      "rel": "item",
      "type": "application/geo+json",
      "file:checksum": "1220e844cd806cc770747c19dae86086a5ce461dc6338bb046bf490c321501b861d0"
    },
    {
      "href": "./BE40_5000_0405.json",
      "rel": "item",
      "type": "application/geo+json",
      "file:checksum": "12207160972117900f571968efccab9dd38a406e34334fd6f1ec01e885f80c2d1db1"
    },
    {
      "href": "./BE40_5000_0406.json",
      "rel": "item",
      "type": "application/geo+json",
      "file:checksum": "12206abf4c4cf7518c08cf90cc84b0400a9f0e437444ed9f87fe1e906356c4c5ddec"
    },
    {
      "href": "./BE40_5000_0407.json",
      "rel": "item",
      "type": "application/geo+json",
      "file:checksum": "12208b17385f2ea53fa03a96a456dcaf1de68ffdff950bba1b715d09108c47e278c3"
    },
    {
      "href": "./BE40_5000_0408.json",
      "rel": "item",
      "type": "application/geo+json",
      "file:checksum": "12205881bf4ef6dc5e57589b11bf0fdbb88dbe17bbcc349077dab32edef561b8e4c0"
    },
    {
      "href": "./BE40_5000_0504.json",
      "rel": "item",
      "type": "application/geo+json",
      "file:checksum": "122019a7b4122f16026382eb7905a050ce9152df4f22a2519d797ca8ad4342c2a656"
    },
    {
      "href": "./BE40_5000_0505.json",
      "rel": "item",
      "type": "application/geo+json",
      "file:checksum": "122092810758cd98c601b98e8d802d2d7a761bd664f4f6676921b48dea1be04aaef6"
    },
    {
      "href": "./BE40_5000_0506.json",
      "rel": "item",
      "type": "application/geo+json",
      "file:checksum": "1220080680e4aa739e780570f8741f083e82df5ac431e9ffd38422cebe1a77542d23"
    },
    {
      "href": "./BE40_5000_0507.json",
      "rel": "item",
      "type": "application/geo+json",
      "file:checksum": "12204593f5b5370d7014ccd49930b718db69408d4a2c1c0adb2954d919570010948b"
    },
    {
      "href": "./BE40_5000_0508.json",
      "rel": "item",
      "type": "application/geo+json",
      "file:checksum": "12202af52c2bb672ef69b408fd28bef22588826737435e4d6a0f29548b8c8035c179"
    },
    {
      "href": "./BE40_5000_0509.json",
      "rel": "item",
      "type": "application/geo+json",
      "file:checksum": "12209e356883279c46ca1345a8f24a2040230be4709a51408585fc052508e1824103"
    },
    {
      "href": "./BE40_5000_0510.json",
      "rel": "item",
      "type": "application/geo+json",
      "file:checksum": "122069aa9825dfacac90f0d7cac8773ad6c39f7794ef2e317dea2475f4b5b8e17167"
    },
    {
      "href": "./BE40_5000_0605.json",
      "rel": "item",
      "type": "application/geo+json",
      "file:checksum": "122057e9167379b8a7b13eb1dc78c5debe21536e3d7edd28fa94dd199be029b28795"
    },
    {
      "href": "./BE40_5000_0606.json",
      "rel": "item",
      "type": "application/geo+json",
      "file:checksum": "1220d3b8d65c39382be74e37f82583811da75aaa61a2a744a36284fe0aeaf60ebb08"
    },
    {
      "href": "./BE40_5000_0607.json",
      "rel": "item",
      "type": "application/geo+json",
      "file:checksum": "122032a40d6461a260518115dac55ad7dfbf0708a6bbffb2023c5c8813360c767aec"
    },
    {
      "href": "./BE40_5000_0608.json",
      "rel": "item",
      "type": "application/geo+json",
      "file:checksum": "122053e9576336c1ec734cea440f272d4e6d63c1d47edfd59266dfbfb809abbf5b6c"
    },
    {
      "href": "./BE40_5000_0701.json",
      "rel": "item",
      "type": "application/geo+json",
      "file:checksum": "122073438c3549c2408e9207dc571b99a91bbf4184621d13cb682fd1429f3939f2a4"
    },
    {
      "href": "./BE40_5000_0702.json",
      "rel": "item",
      "type": "application/geo+json",
      "file:checksum": "1220de53fdb1c10265ab060736b441fc98bec92d9c7b67715fdb127c5f34fb12a846"
    },
    {
      "href": "./BE41_5000_0310.json",
      "rel": "item",
      "type": "application/geo+json",
      "file:checksum": "1220e5c95c8eb28eb52752d562c464222e9bea28cc9c78ed04ae8e8c04b9269c190a"
    },
    {
      "href": "./BE41_5000_0407.json",
      "rel": "item",
      "type": "application/geo+json",
      "file:checksum": "1220b0ad76f3fc146bedd0e5d63c08bd93bc3dadaf3a8b33de40b89c2af3810c61dd"
    },
    {
      "href": "./BE41_5000_0408.json",
      "rel": "item",
      "type": "application/geo+json",
      "file:checksum": "1220cf0cd6dd8759dc9a41ba5cc791db60b57fdb119fa33575ab92f3a18c5c05c683"
    },
    {
      "href": "./BE41_5000_0409.json",
      "rel": "item",
      "type": "application/geo+json",
      "file:checksum": "122025aa86e3842e6f2d6267a258e96f288742399acc361d9ae4f45b670648a371d7"
    },
    {
      "href": "./BE41_5000_0410.json",
      "rel": "item",
      "type": "application/geo+json",
      "file:checksum": "12205e7c22dce5871b71721d1da4109a34436f13c1d1740b0d5bda1b549cc16547b5"
    },
    {
      "href": "./BE41_5000_0501.json",
      "rel": "item",
      "type": "application/geo+json",
      "file:checksum": "12204f1f6d697ca11f1cea1bde3256ab87076bf4a56b2b703f1ec7c5764da57e1c18"
    },
    {
      "href": "./BE41_5000_0502.json",
      "rel": "item",
      "type": "application/geo+json",
      "file:checksum": "12202495c9b47588217b076f7e0a53104b356bd1d02fa5a8e6bab8b93aeacef6381e"
    },
    {
      "href": "./BE41_5000_0503.json",
      "rel": "item",
      "type": "application/geo+json",
      "file:checksum": "122090ddbd66099607f206f221af255c0be309d6108d373eb70340d07dbdaee4fdce"
    },
    {
      "href": "./BE41_5000_0504.json",
      "rel": "item",
      "type": "application/geo+json",
      "file:checksum": "1220ee91efe3066aff48a421a02306baf0059c0100f6451d1d22ac8177c9890e661d"
    },
    {
      "href": "./BE41_5000_0505.json",
      "rel": "item",
      "type": "application/geo+json",
      "file:checksum": "12209df4b78828457cd7e4cef5ed78ccbd6bbe639b7f220e3f2fd45c42a98ca60fae"
    },
    {
      "href": "./BE41_5000_0506.json",
      "rel": "item",
      "type": "application/geo+json",
      "file:checksum": "12203495d6b6605e6ce50ae3e68adc355f76f3e5d857cfc184a3c7fc065e426ae49b"
    },
    {
      "href": "./BE41_5000_0507.json",
      "rel": "item",
      "type": "application/geo+json",
      "file:checksum": "1220f839edf1468894b7a0450883c2a1d61dd81bf3075e48788c8291c8ea70514f1a"
    },
    {
      "href": "./BE41_5000_0601.json",
      "rel": "item",
      "type": "application/geo+json",
      "file:checksum": "1220c9e4e3f3941b26b61712a4d1402b95538c843eb2bbfe413de6301044587d626e"
    },
    {
      "href": "./BE41_5000_0602.json",
      "rel": "item",
      "type": "application/geo+json",
      "file:checksum": "1220e45d1286eae14ce79671dea211311a78b78c6e9ddbafed9e946043df272753a7"
    },
    {
      "href": "./BE41_5000_0603.json",
      "rel": "item",
      "type": "application/geo+json",
      "file:checksum": "12201534a6f59dc14ad14928718a3e5044f5f6384ca4b3b12a77fde29f428fe85fb1"
    },
    {
      "href": "./BE42_5000_0103.json",
      "rel": "item",
      "type": "application/geo+json",
      "file:checksum": "12208fd204c86c91d40738c1e5a7101497a00f41799241efcb19d2f6de9cf54ed947"
    },
    {
      "href": "./BE42_5000_0104.json",
      "rel": "item",
      "type": "application/geo+json",
      "file:checksum": "1220c1cfafa3fafcaff1d29bfbd0db253d3c54135632535884a4eec7459161010b86"
    },
    {
      "href": "./BE42_5000_0105.json",
      "rel": "item",
      "type": "application/geo+json",
      "file:checksum": "1220d62bec421143a89e10a775ee9b8d63638299022b08d83faa227f893771beb083"
    },
    {
      "href": "./BE42_5000_0202.json",
      "rel": "item",
      "type": "application/geo+json",
      "file:checksum": "12202fd8f002bc0cdf2c52a5586c8f51d30ca83a06e0d6cab996532504c8559d7a71"
    },
    {
      "href": "./BE42_5000_0203.json",
      "rel": "item",
      "type": "application/geo+json",
      "file:checksum": "12200dd046cec59d9ccf8c2d93a2e3ad2ba12e20c75fc35674f7e1cdea67a846520e"
    },
    {
      "href": "./BE42_5000_0301.json",
      "rel": "item",
      "type": "application/geo+json",
      "file:checksum": "12204ddaac4f398570481ab9b05d7589e55b26ad21bbd6f34bc4812e5b5a825ffc48"
    },
    {
      "href": "./BE42_5000_0302.json",
      "rel": "item",
      "type": "application/geo+json",
      "file:checksum": "12203c10f10165c7e169ee35aed756b252640a5a7394a3d4b1ea423e254ea9182557"
    },
    {
      "href": "./BF37_5000_0106.json",
      "rel": "item",
      "type": "application/geo+json",
      "file:checksum": "1220046028cfd8e7f1dfce2da3016dea640d38b14c09935050cbbbd69790cbf6fbd5"
    },
    {
      "href": "./BF37_5000_0107.json",
      "rel": "item",
      "type": "application/geo+json",
      "file:checksum": "1220e17fa399ae01763935584302d4044c3e178a0d0248846bb7d821540c078ba745"
    },
    {
      "href": "./BF37_5000_0108.json",
      "rel": "item",
      "type": "application/geo+json",
      "file:checksum": "12203c7c704fb80f4ed9b204070f238ef8d6099bd2cdb5ebf83489b9f4468b6d2759"
    },
    {
      "href": "./BF37_5000_0109.json",
      "rel": "item",
      "type": "application/geo+json",
      "file:checksum": "1220a037ad68ebaa7f95c75d6b4959177b981ade33021c2f5ecb81121e52a9248265"
    },
    {
      "href": "./BF37_5000_0406.json",
      "rel": "item",
      "type": "application/geo+json",
      "file:checksum": "1220dba84be8f17aeff0f2932fdefffe4940e9ac2c2305f6864a3a9ab684e52a2776"
    },
    {
      "href": "./BF37_5000_0706.json",
      "rel": "item",
      "type": "application/geo+json",
      "file:checksum": "122097a2f545a77dfc11e4bc7bc4a0a2c42234ae6de3bfabc548d7e439b5aaae236f"
    },
    {
      "href": "./BF37_5000_0707.json",
      "rel": "item",
      "type": "application/geo+json",
      "file:checksum": "122079244c6b84f600e4841a9454568023635a637cf5b64021c867e9d0a0f15da73f"
    },
    {
      "href": "./BF37_5000_0807.json",
      "rel": "item",
      "type": "application/geo+json",
      "file:checksum": "122090294272ded617d6ddc7189e6d01d4a9f28f90551e5486bb92f22f98819fbce6"
    },
    {
      "href": "./BF38_5000_0704.json",
      "rel": "item",
      "type": "application/geo+json",
      "file:checksum": "1220407ae017a90cb257a13dca1002ce821402c006a3401165f7f1a4e38e43aef8e4"
    },
    {
      "href": "./BF38_5000_0705.json",
      "rel": "item",
      "type": "application/geo+json",
      "file:checksum": "1220db7935266886e842e966f21c5d2b12aa772fb7a4f39a25fa938247ab2981e963"
    },
    {
      "href": "./BF38_5000_0810.json",
      "rel": "item",
      "type": "application/geo+json",
      "file:checksum": "122026a3ff09ce7de6c538422fa008f29284a427a844d4ec4f389e5868538e149f98"
    },
    {
      "href": "./BF38_5000_0910.json",
      "rel": "item",
      "type": "application/geo+json",
      "file:checksum": "12204373d1ae4bb4a666a3ee9fca662e1585076b818559bebc3371e6d9570d94ee5f"
    },
    {
      "href": "./BF39_5000_0901.json",
      "rel": "item",
      "type": "application/geo+json",
      "file:checksum": "1220687b2edf1d1ca3ea9dcd20f58d97013e4a810d42adeed59e330aad9ae77c7647"
    }
  ],
  "providers": [
    { "name": "Toitū Te Whenua Land Information New Zealand", "roles": ["host", "processor"] },
    { "name": "Woolpert", "roles": ["producer"] },
    { "name": "BOPLASS", "roles": ["licensor"] }
  ],
  "linz:lifecycle": "ongoing",
  "linz:geospatial_category": "urban-aerial-photos",
  "linz:region": "bay-of-plenty",
  "linz:security_classification": "unclassified",
  "linz:slug": "bay-of-plenty_2025_0.1m",
  "gsd": 0.1,
  "created": "2026-01-25T22:18:08Z",
  "updated": "2026-01-25T22:18:08Z",
  "extent": {
    "spatial": { "bbox": [[176.0634013, -38.4879404, 178.1069416, -37.4993267]] },
    "temporal": { "interval": [["2025-10-30T11:00:00Z", "2025-12-07T11:00:00Z"]] }
  },
  "assets": {
    "capture_area": {
      "href": "./capture-area.geojson",
      "title": "Capture area",
      "description": "Boundary of the total capture area for this collection. Excludes nodata areas in the source data. Geometries are simplified.",
      "type": "application/geo+json",
      "roles": ["metadata"],
      "file:checksum": "12207dad89322e990a87dcd643671415d867e152000d871c45c136664e0fb48283b2",
      "file:size": 24313
    }
  },
  "stac_extensions": ["https://stac-extensions.github.io/file/v2.0.0/schema.json"]
}
