{
  "type": "Feature",
  "stac_version": "1.0.0",
  "id": "BN33_500_079013",
  "links": [
    { "rel": "self", "href": "./BN33_500_079013.json", "type": "application/json" },
    { "rel": "collection", "href": "./collection.json", "type": "application/json" },
    { "rel": "parent", "href": "./collection.json", "type": "application/json" }
  ],
  "assets": {
    "visual": {
      "href": "./BN33_500_079013.tiff",
      "type": "image/tiff; application=geotiff; profile=cloud-optimized",
      "file:checksum": "122015a9049f952a378fc236053523916c73c650d173c1f49f5fcd59c40bee8dfb79"
    }
  },
  "stac_extensions": ["https://stac-extensions.github.io/file/v2.0.0/schema.json"],
  "properties": { "start_datetime": "2021-01-13T11:00:00Z", "end_datetime": "2021-01-13T11:00:00Z", "datetime": null },
  "geometry": {
    "type": "Polygon",
    "coordinates": [
      [
        [175.1665114, -40.7573583],
        [175.1666167, -40.7605991],
        [175.169458, -40.7605457],
        [175.1693526, -40.7573049],
        [175.1665114, -40.7573583]
      ]
    ]
  },
  "bbox": [175.1665114, -40.7605991, 175.169458, -40.7573049],
  "collection": "01GSVGECSVTZB83TMR4N34E4D6"
}
