{
  "type": "Feature",
  "stac_version": "1.0.0",
  "id": "BE35_1000_0609",
  "links": [
    { "rel": "self", "href": "./BE35_1000_0609.json", "type": "application/json" },
    { "rel": "collection", "href": "./collection.json", "type": "application/json" },
    { "rel": "parent", "href": "./collection.json", "type": "application/json" }
  ],
  "assets": {
    "visual": {
      "href": "./BE35_1000_0609.tiff",
      "type": "image/tiff; application=geotiff; profile=cloud-optimized",
      "file:checksum": "1220159b0e87f6c3b721d0af2e0cede4a36dcf0305aefb28c0af05418f53fdd896c4"
    }
  },
  "stac_extensions": ["https://stac-extensions.github.io/file/v2.0.0/schema.json"],
  "properties": { "start_datetime": "2021-01-30T11:00:00Z", "end_datetime": "2021-02-18T11:00:00Z", "datetime": null },
  "geometry": {
    "type": "Polygon",
    "coordinates": [
      [
        [175.6379783, -37.9324278],
        [175.6382102, -37.9389103],
        [175.643667, -37.9387877],
        [175.6434346, -37.9323053],
        [175.6379783, -37.9324278]
      ]
    ]
  },
  "bbox": [175.6379783, -37.9389103, 175.643667, -37.9323053],
  "collection": "01GSXJB0F04QD6HG93ABRCE2YG"
}
