{
  "type": "Feature",
  "stac_version": "1.0.0",
  "id": "BL38_1000_1237",
  "links": [
    { "rel": "self", "href": "./BL38_1000_1237.json", "type": "application/json" },
    { "rel": "collection", "href": "./collection.json", "type": "application/json" },
    { "rel": "parent", "href": "./collection.json", "type": "application/json" }
  ],
  "assets": {
    "visual": {
      "href": "./BL38_1000_1237.tiff",
      "type": "image/tiff; application=geotiff; profile=cloud-optimized",
      "file:checksum": "1220916fa2e1da8d892ecb93fdee19226f9cfc635682f1429d5ba69e6ab3c5ca8bee"
    }
  },
  "stac_extensions": ["https://stac-extensions.github.io/file/v2.0.0/schema.json"],
  "properties": { "start_datetime": "2023-02-18T11:00:00Z", "end_datetime": "2023-02-20T11:00:00Z", "datetime": null },
  "geometry": {
    "type": "Polygon",
    "coordinates": [
      [
        [176.7104559, -39.8880022],
        [176.7108054, -39.8944757],
        [176.7164082, -39.8942961],
        [176.7160582, -39.8878226],
        [176.7104559, -39.8880022]
      ]
    ]
  },
  "bbox": [176.7104559, -39.8944757, 176.7164082, -39.8878226],
  "collection": "01GTE4ZWCXRGNX6W0VC3SR6VJ5"
}
