{
  "type": "Feature",
  "stac_version": "1.0.0",
  "id": "BP32_500_013073",
  "links": [
    { "rel": "self", "href": "./BP32_500_013073.json", "type": "application/json" },
    { "rel": "collection", "href": "./collection.json", "type": "application/json" },
    { "rel": "parent", "href": "./collection.json", "type": "application/json" }
  ],
  "assets": {
    "visual": {
      "href": "./BP32_500_013073.tiff",
      "type": "image/tiff; application=geotiff; profile=cloud-optimized",
      "file:checksum": "1220c1772ccfbc15298051e5bfe974924a964e1d8a26af8e70b2490b9fce3764f015"
    }
  },
  "stac_extensions": ["https://stac-extensions.github.io/file/v2.0.0/schema.json"],
  "properties": { "start_datetime": "2017-02-23T11:00:00Z", "end_datetime": "2017-02-23T11:00:00Z", "datetime": null },
  "geometry": {
    "type": "Polygon",
    "coordinates": [
      [
        [175.056256, -40.8696302],
        [175.0563564, -40.8728711],
        [175.0592027, -40.8728203],
        [175.0591023, -40.8695794],
        [175.056256, -40.8696302]
      ]
    ]
  },
  "bbox": [175.056256, -40.8728711, 175.0592027, -40.8695794],
  "collection": "01GYDR7DQB37DVG2VKCSDD5FPG"
}
