{
  "type": "Feature",
  "stac_version": "1.0.0",
  "id": "BM34_1000_3043",
  "links": [
    { "rel": "self", "href": "./BM34_1000_3043.json", "type": "application/json" },
    { "rel": "collection", "href": "./collection.json", "type": "application/json" },
    { "rel": "parent", "href": "./collection.json", "type": "application/json" }
  ],
  "assets": {
    "visual": {
      "href": "./BM34_1000_3043.tiff",
      "type": "image/tiff; application=geotiff; profile=cloud-optimized",
      "file:checksum": "122044988e0d89081c3c4f0a9bed582884f849749001762c2a65bce2099e5e051a85"
    }
  },
  "stac_extensions": ["https://stac-extensions.github.io/file/v2.0.0/schema.json"],
  "properties": { "start_datetime": "2015-02-11T11:00:00Z", "end_datetime": "2015-02-17T11:00:00Z", "datetime": null },
  "geometry": {
    "type": "Polygon",
    "coordinates": [
      [
        [175.6397638, -40.358377],
        [175.6400167, -40.3648568],
        [175.6456641, -40.3647276],
        [175.6454106, -40.3582479],
        [175.6397638, -40.358377]
      ]
    ]
  },
  "bbox": [175.6397638, -40.3648568, 175.6456641, -40.3582479],
  "collection": "01GY95TFAJGA1D75ZPBV6M3NTA"
}
