{
  "type": "Feature",
  "stac_version": "1.0.0",
  "id": "AV27_5000_0306",
  "links": [
    { "rel": "self", "href": "./AV27_5000_0306.json", "type": "application/json" },
    { "rel": "collection", "href": "./collection.json", "type": "application/json" },
    { "rel": "parent", "href": "./collection.json", "type": "application/json" }
  ],
  "assets": {
    "visual": {
      "href": "./AV27_5000_0306.tiff",
      "type": "image/tiff; application=geotiff; profile=cloud-optimized",
      "file:checksum": "1220014a968a00777823c2ff9f9dd41f343baf18ae4e312109e00a9c3e4ba78e48c5"
    }
  },
  "stac_extensions": ["https://stac-extensions.github.io/file/v2.0.0/schema.json"],
  "properties": { "start_datetime": "2014-11-08T11:00:00Z", "end_datetime": "2016-06-30T12:00:00Z", "datetime": null },
  "geometry": {
    "type": "Polygon",
    "coordinates": [
      [
        [173.5264795, -35.0724116],
        [173.5266882, -35.1048725],
        [173.5530215, -35.1047552],
        [173.5528025, -35.0722944],
        [173.5264795, -35.0724116]
      ]
    ]
  },
  "bbox": [173.5264795, -35.1048725, 173.5530215, -35.0722944],
  "collection": "01GY93MM6MA315C7HE9S035CJR"
}
