{
  "type": "Feature",
  "stac_version": "1.0.0",
  "id": "BS29_500_003041",
  "links": [
    { "rel": "self", "href": "./BS29_500_003041.json", "type": "application/json" },
    { "rel": "collection", "href": "./collection.json", "type": "application/json" },
    { "rel": "parent", "href": "./collection.json", "type": "application/json" }
  ],
  "assets": {
    "visual": {
      "href": "./BS29_500_003041.tiff",
      "type": "image/tiff; application=geotiff; profile=cloud-optimized",
      "file:checksum": "1220b92f8688dafeda0123da146384b48998594f2a63a185f3f7f16eba2730dec5f7"
    }
  },
  "stac_extensions": ["https://stac-extensions.github.io/file/v2.0.0/schema.json"],
  "properties": { "start_datetime": "2020-10-15T11:00:00Z", "end_datetime": "2021-01-14T11:00:00Z", "datetime": null },
  "geometry": {
    "type": "Polygon",
    "coordinates": [
      [
        [174.1270652, -41.8228347],
        [174.127122, -41.8260766],
        [174.1300116, -41.8260482],
        [174.1299545, -41.8228063],
        [174.1270652, -41.8228347]
      ]
    ]
  },
  "bbox": [174.1270652, -41.8260766, 174.1300116, -41.8228063],
  "collection": "01GSTYW47MV21RQX82J87SNKZB"
}
