{
  "type": "Feature",
  "stac_version": "1.0.0",
  "id": "BQ26_1000_4416",
  "links": [
    { "rel": "self", "href": "./BQ26_1000_4416.json", "type": "application/json" },
    { "rel": "collection", "href": "./collection.json", "type": "application/json" },
    { "rel": "parent", "href": "./collection.json", "type": "application/json" }
  ],
  "assets": {
    "visual": {
      "href": "./BQ26_1000_4416.tiff",
      "type": "image/tiff; application=geotiff; profile=cloud-optimized",
      "file:checksum": "1220b94fdd0d488107477a39ba404d6ca3fd3b93f85acb8ce2798fd97f6fe7cdb7b6"
    }
  },
  "stac_extensions": ["https://stac-extensions.github.io/file/v2.0.0/schema.json"],
  "properties": { "start_datetime": "2022-08-22T12:00:00Z", "end_datetime": "2022-09-05T12:00:00Z", "datetime": null },
  "geometry": {
    "type": "Polygon",
    "coordinates": [
      [
        [173.2298729, -41.4519926],
        [173.2298958, -41.458478],
        [173.2356432, -41.4584663],
        [173.2356197, -41.451981],
        [173.2298729, -41.4519926]
      ]
    ]
  },
  "bbox": [173.2298729, -41.458478, 173.2356432, -41.451981],
  "collection": "01GG8ZW45194S82WN4ZYV9DRJJ"
}
