{
  "type": "Feature",
  "stac_version": "1.0.0",
  "id": "BS29_5000_0401",
  "links": [
    { "rel": "self", "href": "./BS29_5000_0401.json", "type": "application/json" },
    { "rel": "collection", "href": "./collection.json", "type": "application/json" },
    { "rel": "parent", "href": "./collection.json", "type": "application/json" }
  ],
  "assets": {
    "visual": {
      "href": "./BS29_5000_0401.tiff",
      "type": "image/tiff; application=geotiff; profile=cloud-optimized",
      "file:checksum": "1220c2eb52327b4b8c7a153508b076501032507f4d2ba1363885e493d75192b42302"
    }
  },
  "stac_extensions": ["https://stac-extensions.github.io/file/v2.0.0/schema.json"],
  "properties": { "start_datetime": "2021-12-31T11:00:00Z", "end_datetime": "2022-03-30T11:00:00Z", "datetime": null },
  "geometry": {
    "type": "Polygon",
    "coordinates": [
      [
        [174.0129192, -41.9146858],
        [174.0134323, -41.9471051],
        [174.042383, -41.9468459],
        [174.0418552, -41.9144269],
        [174.0129192, -41.9146858]
      ]
    ]
  },
  "bbox": [174.0129192, -41.9471051, 174.042383, -41.9144269],
  "collection": "01GPA4VXSPMSH2NYGWN26A74GG"
}
