{
  "type": "Feature",
  "stac_version": "1.0.0",
  "id": "AZ34_1000_0144",
  "links": [
    { "rel": "self", "href": "./AZ34_1000_0144.json", "type": "application/json" },
    { "rel": "collection", "href": "./collection.json", "type": "application/json" },
    { "rel": "parent", "href": "./collection.json", "type": "application/json" }
  ],
  "assets": {
    "visual": {
      "href": "./AZ34_1000_0144.tiff",
      "type": "image/tiff; application=geotiff; profile=cloud-optimized",
      "file:checksum": "122033eecbcf0e086ba2eba255577ae611fa3638a955721913bec4a773df56894d4c"
    }
  },
  "stac_extensions": ["https://stac-extensions.github.io/file/v2.0.0/schema.json"],
  "properties": { "start_datetime": "2017-03-14T11:00:00Z", "end_datetime": "2017-05-05T12:00:00Z", "datetime": null },
  "geometry": {
    "type": "Polygon",
    "coordinates": [
      [
        [175.501124, -36.280832],
        [175.5013311, -36.287317],
        [175.5066712, -36.2872051],
        [175.5064637, -36.2807201],
        [175.501124, -36.280832]
      ]
    ]
  },
  "bbox": [175.501124, -36.287317, 175.5066712, -36.2807201],
  "collection": "01GY9F9JTJ45F1D1TQK4GQ4M1F"
}
