{
  "type": "Feature",
  "stac_version": "1.0.0",
  "id": "BD36_500_024072",
  "links": [
    { "rel": "self", "href": "./BD36_500_024072.json", "type": "application/json" },
    { "rel": "collection", "href": "./collection.json", "type": "application/json" },
    { "rel": "parent", "href": "./collection.json", "type": "application/json" }
  ],
  "assets": {
    "visual": {
      "href": "./BD36_500_024072.tiff",
      "type": "image/tiff; application=geotiff; profile=cloud-optimized",
      "file:checksum": "12200dbb670812b5c96c3e1809dc173d96e4202e0ea6e72d20995af147e3c4fe07d5"
    }
  },
  "stac_extensions": ["https://stac-extensions.github.io/file/v2.0.0/schema.json"],
  "properties": { "start_datetime": "2020-12-15T11:00:00Z", "end_datetime": "2020-12-15T11:00:00Z", "datetime": null },
  "geometry": {
    "type": "Polygon",
    "coordinates": [
      [
        [176.0491261, -37.6402909],
        [176.0492586, -37.6435311],
        [176.0519752, -37.6434608],
        [176.0518425, -37.6402206],
        [176.0491261, -37.6402909]
      ]
    ]
  },
  "bbox": [176.0491261, -37.6435311, 176.0519752, -37.6402206],
  "collection": "01GSVM1JVWNCRKDWSYKRJNEAJA"
}
